<?xml version="1.0" encoding="utf-8"?>
<IncrementalBankBuild Version="6" Flags="240381544">
	<Platform GUID="{B45E3EC8-EB62-4C55-B5E6-599317BCD1FA}">
		<Banks>
			<Language ID="393239870">
				<File Name="Combat" Hash="599961103" Timestamp="131955998746750980"/>
				<File Name="Init" Hash="1768916305" Timestamp="131955989788585170"/>
				<File Name="Punch" Hash="1680762432" Timestamp="131955963627862399"/>
			</Language>
		</Banks>
		<XMLInfo>
			<Language ID="-1">
				<File Name="" Hash="1688577218" Timestamp="131955998746820936"/>
			</Language>
		</XMLInfo>
	</Platform>
</IncrementalBankBuild>
