{"time_manager":{},"window":{"borderless":false,"fullscreen":false,"resizable":false,"fulldesktop":false,"adapt_screen":true,"width":1166,"height":568,"adaptable_offsetx":200,"adaptable_offsety":200,"brightness":1},"camera":{},"input":{},"importer":{},"scene":{},"debug":{},"resource manager":{},"gui":{"hierarchy":true,"obj_inspector":true,"primitive":true,"about":false,"configuration":true,"log":false,"time_control":true,"quadtree_config":false,"camera_menu":false,"asset_window":true,"resources_window":false},"renderer3d":{}}
